python_heapq/__init__.py
python_heapq-0.0.1.dist-info/METADATA
python_heapq-0.0.1.dist-info/WHEEL
python_heapq-0.0.1.dist-info/RECORD
