Metadata-Version: 2.3
Name: python-heapq
Version: 0.0.1
Summary: class based heap queue algorithm implemented in python
Requires-Python: >=3.10
